telepostkeeper/encryption.py
telepostkeeper/frontend.py
telepostkeeper/telepostkeeper.py
telepostkeeper/templates/base.html
telepostkeeper/templates/chat.html
telepostkeeper/templates/chat.md
telepostkeeper/templates/forwardPostContent.html
telepostkeeper/templates/month.html
telepostkeeper/templates/month.md
telepostkeeper/templates/store.html
telepostkeeper/templates/store.md
telepostkeeper/templates/year.html
telepostkeeper/templates/year.md
telepostkeeper/utils.py
telepostkeeper-0.1.33.dist-info/METADATA
telepostkeeper-0.1.33.dist-info/WHEEL
telepostkeeper-0.1.33.dist-info/entry_points.txt
telepostkeeper-0.1.33.dist-info/RECORD
