Metadata-Version: 2.3
Name: telepostkeeper
Version: 0.1.33
Summary: 💌 A Python tool to automate and manage Telegram channel content with encryption and scheduling support.
Author: Your Name
Author-email: your.email@example.com
Requires-Python: >=3.9
Classifier: Programming Language :: Python :: 3
Classifier: Programming Language :: Python :: 3.9
Classifier: Programming Language :: Python :: 3.10
Classifier: Programming Language :: Python :: 3.11
Classifier: Programming Language :: Python :: 3.12
Classifier: Programming Language :: Python :: 3.13
Requires-Dist: jinja2 (>=3.1.2)
Requires-Dist: pycryptodome (>=3.18.0)
Requires-Dist: python-telegram-bot (>=20.3)
Requires-Dist: pyyaml (>=6.0.1)
